.gitignore
LICENSE
Makefile
README.rst
requirements.txt
setup.cfg
setup.py
packaging/rpm/statusinfo.spec
statusinfo/.gitignore
statusinfo/__init__.py
statusinfo/__main__.py
statusinfo/arguments.py
statusinfo/exception.py
statusinfo/gatherer.py
statusinfo/logging.py
statusinfo/statusinfo.py
statusinfo/util.py
statusinfo/version.py
statusinfo.egg-info/PKG-INFO
statusinfo.egg-info/SOURCES.txt
statusinfo.egg-info/dependency_links.txt
statusinfo.egg-info/entry_points.txt
statusinfo.egg-info/top_level.txt