Metadata-Version: 1.2
Name: statusinfo
Version: 0.1.6
Summary: A tool for gathering status information.
Home-page: https://pypi.python.org/pypi/statusinfo
Author: eikendev
Author-email: raphael@eiken.dev
License: MIT
Keywords: status,information,gathering
Platform: UNKNOWN
Classifier: Development Status :: 4 - Beta
Classifier: Intended Audience :: Developers
Classifier: License :: OSI Approved :: MIT License
Classifier: Programming Language :: Python :: 3
Classifier: Topic :: Utilities
Classifier: Environment :: Console
Classifier: Operating System :: POSIX
Requires-Python: >=3
